pfdicom_tagExtract/__init__.py
pfdicom_tagExtract/__main__.py
pfdicom_tagExtract/pfdicom_tagExtract.py
pfdicom_tagExtract-3.1.0.dist-info/LICENSE
pfdicom_tagExtract-3.1.0.dist-info/METADATA
pfdicom_tagExtract-3.1.0.dist-info/WHEEL
pfdicom_tagExtract-3.1.0.dist-info/entry_points.txt
pfdicom_tagExtract-3.1.0.dist-info/top_level.txt
pfdicom_tagExtract-3.1.0.dist-info/RECORD
