Metadata-Version: 2.1
Name: pfdicom-tagExtract
Version: 3.1.0
Summary: Extract DICOM header info -- part of the pf* family.
Home-page: https://github.com/FNNDSC/pfdicom_tagExtract
Author: FNNDSC
Author-email: dev@babymri.org
License: MIT
License-File: LICENSE
Requires-Dist: pfdicom
Requires-Dist: matplotlib
Requires-Dist: pillow
